{
    "menu": [
        {
            "active": 1, 
            "activeWire": false, 
            "command": "cmds.createNode(\"file\", False)", 
            "commandType": "createnode", 
            "context": "SOP", 
            "icon": "SOP_file", 
            "index": 0, 
            "isMenu": false, 
            "label": "File", 
            "menuCollection": "< Not Linked >", 
            "nodetype": "file"
        }, 
        {
            "active": 1, 
            "activeWire": false, 
            "command": "cmds.createNode(\"alembic\", False)", 
            "commandType": "createnode", 
            "context": "SOP", 
            "icon": "SOP_alembic", 
            "index": 1, 
            "isMenu": false, 
            "label": "Alembic", 
            "menuCollection": "< Not Linked >", 
            "nodetype": "alembic"
        }, 
        {
            "active": 0, 
            "activeWire": false, 
            "command": "cmds.createNode(\"null\", False)", 
            "commandType": "createnode", 
            "context": "SOP", 
            "icon": "MISC_python", 
            "index": 2, 
            "isMenu": 0, 
            "label": "", 
            "menuCollection": "", 
            "nodetype": "null"
        }, 
        {
            "active": 0, 
            "activeWire": false, 
            "command": "cmds.createNode(\"null\", False)", 
            "commandType": "createnode", 
            "context": "SOP", 
            "icon": "MISC_python", 
            "index": 3, 
            "isMenu": 0, 
            "label": "", 
            "menuCollection": "", 
            "nodetype": "null"
        }, 
        {
            "active": 0, 
            "activeWire": false, 
            "command": "cmds.createNode(\"null\", False)", 
            "commandType": "createnode", 
            "context": "SOP", 
            "icon": "MISC_python", 
            "index": 4, 
            "isMenu": 0, 
            "label": "", 
            "menuCollection": "", 
            "nodetype": "null"
        }, 
        {
            "active": 0, 
            "activeWire": false, 
            "command": "cmds.createNode(\"null\", False)", 
            "commandType": "createnode", 
            "context": "SOP", 
            "icon": "MISC_python", 
            "index": 5, 
            "isMenu": 0, 
            "label": "", 
            "menuCollection": "", 
            "nodetype": "null"
        }, 
        {
            "active": 0, 
            "activeWire": false, 
            "command": "cmds.createNode(\"null\", False)", 
            "commandType": "createnode", 
            "context": "SOP", 
            "icon": "MISC_python", 
            "index": 6, 
            "isMenu": 0, 
            "label": "", 
            "menuCollection": "", 
            "nodetype": "null"
        }, 
        {
            "active": 0, 
            "activeWire": false, 
            "command": "cmds.createNode(\"null\", False)", 
            "commandType": "createnode", 
            "context": "SOP", 
            "icon": "MISC_python", 
            "index": 7, 
            "isMenu": 0, 
            "label": "", 
            "menuCollection": "", 
            "nodetype": "null"
        }
    ]
}